funny_numbers-0.2.0.dist-info/METADATA
funny_numbers-0.2.0.dist-info/WHEEL
funny_numbers-0.2.0.dist-info/entry_points.txt
funny_numbers/__init__.py
funny_numbers/_core.abi3.so
funny_numbers/_core.pyi
funny_numbers/py.typed
funny_numbers-0.2.0.dist-info/RECORD
